secure_scaffold/__init__.py
secure_scaffold/commands.py
secure_scaffold/config.py
secure_scaffold/factories.py
secure_scaffold/settings.py
secure_scaffold/xsrf.py
secure_scaffold/contrib/__init__.py
secure_scaffold/contrib/appengine/__init__.py
secure_scaffold/contrib/appengine/users.py
secure_scaffold/contrib/appengine/tests/__init__.py
secure_scaffold/contrib/appengine/tests/test_users.py
secure_scaffold/contrib/cloud_tasks/__init__.py
secure_scaffold/contrib/cloud_tasks/tasks.py
secure_scaffold/contrib/cloud_tasks/tests/__init__.py
secure_scaffold/contrib/cloud_tasks/tests/test_tasks.py
secure_scaffold/contrib/db/__init__.py
secure_scaffold/contrib/db/models.py
secure_scaffold/contrib/db/engine/__init__.py
secure_scaffold/contrib/db/engine/base.py
secure_scaffold/contrib/db/engine/datastore.py
secure_scaffold/contrib/db/engine/firestore.py
secure_scaffold/contrib/db/engine/tests/__init__.py
secure_scaffold/contrib/db/engine/tests/test_datastore.py
secure_scaffold/contrib/db/engine/tests/test_firestore.py
secure_scaffold/contrib/db/tests/__init__.py
secure_scaffold/contrib/db/tests/test_models.py
secure_scaffold/contrib/users/auth.py
secure_scaffold/contrib/users/templates/login.html
secure_scaffold/contrib/users/tests/test_auth.py
secure_scaffold/project_template/README.md.tpl
secure_scaffold/project_template/app.yaml.tpl
secure_scaffold/project_template/main.py.tpl
secure_scaffold/project_template/models.py.tpl
secure_scaffold/project_template/requirements.txt.tpl
secure_scaffold/project_template/settings.py.tpl
secure_scaffold/project_template/tasks.py.tpl
secure_scaffold/tests/test_config.py
secure_scaffold/tests/test_factories.py
secure_scaffold/tests/test_xsrf.py
Toaster_Secure_Scaffold_RC-0.8.2.dist-info/AUTHORS
Toaster_Secure_Scaffold_RC-0.8.2.dist-info/LICENSE
Toaster_Secure_Scaffold_RC-0.8.2.dist-info/METADATA
Toaster_Secure_Scaffold_RC-0.8.2.dist-info/WHEEL
Toaster_Secure_Scaffold_RC-0.8.2.dist-info/entry_points.txt
Toaster_Secure_Scaffold_RC-0.8.2.dist-info/top_level.txt
Toaster_Secure_Scaffold_RC-0.8.2.dist-info/RECORD
