Metadata-Version: 2.1
Name: Toaster-Secure-Scaffold-RC
Version: 0.8.2
Summary: Secure Scaffold for Google App Engine
Home-page: https://github.com/toasterco/gae-secure-scaffold-python
Author: Toaster Ltd.
Author-email: developers@toaster.co
License: UNKNOWN
Platform: UNKNOWN
Classifier: Programming Language :: Python :: 3.7
Classifier: Programming Language :: Python :: 3 :: Only
Classifier: License :: OSI Approved :: Apache Software License
Classifier: Operating System :: OS Independent
Requires-Dist: flask (==1.0.2)
Requires-Dist: click (==7.0)
Provides-Extra: datastore
Requires-Dist: google-cloud-datastore (==1.8.0) ; extra == 'datastore'
Provides-Extra: firestore
Requires-Dist: google-cloud-firestore (==1.2.0) ; extra == 'firestore'
Provides-Extra: tasks
Requires-Dist: google-cloud-tasks (==1.1.0) ; extra == 'tasks'
